PyQt5/Qt5/bin/Qt5DesignerComponents.dll
PyQt5/Qt5/bin/designer.exe
PyQt5/Qt5/bin/qt.conf
PyQt5/Qt5/translations/designer_ar.qm
PyQt5/Qt5/translations/designer_en.qm
PyQt5/Qt5/translations/designer_fr.qm
pyqt5_qt5_designer/__about__.py
pyqt5_qt5_designer/__init__.py
pyqt5_qt5_designer/designer_runner.py
pyqt5_qt5_designer-0.0.13.dist-info/METADATA
pyqt5_qt5_designer-0.0.13.dist-info/WHEEL
pyqt5_qt5_designer-0.0.13.dist-info/entry_points.txt
pyqt5_qt5_designer-0.0.13.dist-info/licenses/LICENSE.txt
pyqt5_qt5_designer-0.0.13.dist-info/RECORD
