Metadata-Version: 2.3
Name: pyqt5_qt5_designer
Version: 0.0.13
Project-URL: Documentation, https://github.com/selmen2004/pyqt5_qt5_designer#readme
Project-URL: Issues, https://github.com/selmen2004/pyqt5_qt5_designer/issues
Project-URL: Source, https://github.com/selmen2004/pyqt5_qt5_designer
Author-email: Selmen Arous <selmen.arous@gmail.com>
License-Expression: MIT
License-File: LICENSE.txt
Classifier: Development Status :: 4 - Beta
Classifier: Programming Language :: Python
Classifier: Programming Language :: Python :: 3.8
Classifier: Programming Language :: Python :: 3.9
Classifier: Programming Language :: Python :: 3.10
Classifier: Programming Language :: Python :: 3.11
Classifier: Programming Language :: Python :: 3.12
Classifier: Programming Language :: Python :: Implementation :: CPython
Classifier: Programming Language :: Python :: Implementation :: PyPy
Requires-Python: >=3.8
Requires-Dist: pyqt5
